[
  {
    "title": "Mid-Semester Test",
    "content": "The mid-semester test for all 200-level students is scheduled for this week. Please review all course materials.",
    "date": "23/06/2026"
  },
  {
    "title": "Course Registration",
    "content": "Course registration for the next semester is now open. Register before the deadline.",
    "date": "15/06/2026"
  },
  {
    "title": "Departmental Meeting",
    "content": "All students are required to attend the departmental meeting on this date.",
    "date": "19/06/2026"
  },
  {
    "title": "Exam Schedule Released",
    "content": "The official exam timetable for end-of-semester exams has been released.",
    "date": "28/06/2026"
  },
  {
    "title": "Student ID Renewal",
    "content": "Students with expired IDs should report to the student affairs office for renewal.",
    "date": "10/06/2026"
  }
]
